{
  "content": [
    {
      "content": null,
      "created": "2025-05-13T23:51:46.150295Z",
      "format": null,
      "hash": null,
      "hash_algorithm": null,
      "last_modified": "2025-05-13T23:51:02.115898Z",
      "mimetype": null,
      "name": "DA02.ipynb",
      "path": "DA02/DA02.ipynb",
      "size": 12090,
      "type": "notebook",
      "writable": true
    }
  ],
  "created": "2025-05-13T23:51:46.149295Z",
  "format": "json",
  "hash": null,
  "hash_algorithm": null,
  "last_modified": "2025-05-13T23:51:46.149295Z",
  "mimetype": null,
  "name": "DA02",
  "path": "DA02",
  "size": null,
  "type": "directory",
  "writable": true
}